{
  "id": "4797085",
  "name": "cv",
  "font_family": "iconfont",
  "css_prefix_text": "icon-",
  "description": "",
  "glyphs": [
    {
      "icon_id": "4766918",
      "name": "mail",
      "font_class": "mail",
      "unicode": "e7de",
      "unicode_decimal": 59358
    },
    {
      "icon_id": "4766970",
      "name": "phone",
      "font_class": "phone",
      "unicode": "e7e3",
      "unicode_decimal": 59363
    },
    {
      "icon_id": "4936678",
      "name": "phone-fill",
      "font_class": "phone-fill",
      "unicode": "e86d",
      "unicode_decimal": 59501
    },
    {
      "icon_id": "4936690",
      "name": "mail-fill",
      "font_class": "mail-fill",
      "unicode": "e86f",
      "unicode_decimal": 59503
    },
    {
      "icon_id": "4936991",
      "name": "wechat-fill",
      "font_class": "wechat-fill",
      "unicode": "e883",
      "unicode_decimal": 59523
    },
    {
      "icon_id": "4937000",
      "name": "github-fill",
      "font_class": "github-fill",
      "unicode": "e885",
      "unicode_decimal": 59525
    }
  ]
}
